kvlang/__init__.py
kvlang/common.py
kvlang/grammar.py
kvlang/kv.lark
kvlang/parser.py
kvlang/transformer.py
kvlang-1.0.1.dist-info/licenses/LICENSE.txt
kvlang-1.0.1.dist-info/METADATA
kvlang-1.0.1.dist-info/WHEEL
kvlang-1.0.1.dist-info/top_level.txt
kvlang-1.0.1.dist-info/RECORD
