Metadata-Version: 2.4
Name: kvlang
Version: 1.0.1
Home-page: https://github.com/KeyWeeUsr/kvlang
Download-URL: https://github.com/KeyWeeUsr/kvlang/tarball/1.0.1
Author: Peter Badida
Author-email: keyweeusr@gmail.com
License: MIT
Classifier: Development Status :: 3 - Alpha
Classifier: Intended Audience :: Developers
Classifier: Programming Language :: Python :: 3
Classifier: Programming Language :: Python :: 3 :: Only
License-File: LICENSE.txt
Requires-Dist: lark>=1.2.2
Provides-Extra: dev
Requires-Dist: pycodestyle; extra == "dev"
Requires-Dist: pylint; extra == "dev"
Requires-Dist: mypy; extra == "dev"
Requires-Dist: types-setuptools; extra == "dev"
Requires-Dist: sh; extra == "dev"
Requires-Dist: sphinx; extra == "dev"
Provides-Extra: kivy
Requires-Dist: kivy>=2.3.1; extra == "kivy"
Provides-Extra: release
Requires-Dist: wheel; extra == "release"
Requires-Dist: twine; extra == "release"
Requires-Dist: sh; extra == "release"
Dynamic: author
Dynamic: author-email
Dynamic: classifier
Dynamic: description
Dynamic: description-content-type
Dynamic: download-url
Dynamic: home-page
Dynamic: license
Dynamic: license-file
Dynamic: provides-extra
Dynamic: requires-dist
